odoo/addons/l10n_nl_bsn/README.rst
odoo/addons/l10n_nl_bsn/__init__.py
odoo/addons/l10n_nl_bsn/__manifest__.py
odoo/addons/l10n_nl_bsn/i18n/l10n_nl_bsn.pot
odoo/addons/l10n_nl_bsn/i18n/nl.po
odoo/addons/l10n_nl_bsn/models/__init__.py
odoo/addons/l10n_nl_bsn/models/res_partner.py
odoo/addons/l10n_nl_bsn/static/description/icon.png
odoo/addons/l10n_nl_bsn/tests/__init__.py
odoo/addons/l10n_nl_bsn/tests/test_l10n_nl_bsn.py
odoo/addons/l10n_nl_bsn/views/res_partner.xml
odoo11_addon_l10n_nl_bsn-11.0.1.1.0.dist-info/METADATA
odoo11_addon_l10n_nl_bsn-11.0.1.1.0.dist-info/WHEEL
odoo11_addon_l10n_nl_bsn-11.0.1.1.0.dist-info/top_level.txt
odoo11_addon_l10n_nl_bsn-11.0.1.1.0.dist-info/RECORD
